{"created_at":"Thu Jul 23 11:24:54 +0000 2020","id":1286261000145174528,"id_str":"1286261000145174528","text":"@Louis_Tomlinson @NiallOfficial @Harry_Styles @LiamPayne @zaynmalik love you always and forever","display_text_range":[68,95],"source":"\u003ca href=\"http:\/\/twitter.com\/download\/android\" rel=\"nofollow\"\u003eTwitter for Android\u003c\/a\u003e","truncated":false,"in_reply_to_status_id":1286259345802625025,"in_reply_to_status_id_str":"1286259345802625025","in_reply_to_user_id":84279963,"in_reply_to_user_id_str":"84279963","in_reply_to_screen_name":"Louis_Tomlinson","user":{"id":3058169685,"id_str":"3058169685","name":"Eve loves 1D","screen_name":"evevergaraa","location":"Misiones, Argentina","url":null,"description":"mi devoci\u00f3n por one direction y shawn mendes es demasiado grande","translator_type":"none","protected":false,"verified":false,"followers_count":1309,"friends_count":1837,"listed_count":2,"favourites_count":120381,"statuses_count":44303,"created_at":"Tue Feb 24 05:51:18 +0000 2015","utc_offset":null,"time_zone":null,"geo_enabled":true,"lang":null,"contributors_enabled":false,"is_translator":false,"profile_background_color":"000000","profile_background_image_url":"http:\/\/abs.twimg.com\/images\/themes\/theme1\/bg.png","profile_background_image_url_https":"https:\/\/abs.twimg.com\/images\/themes\/theme1\/bg.png","profile_background_tile":false,"profile_link_color":"19CF86","profile_sidebar_border_color":"000000","profile_sidebar_fill_color":"000000","profile_text_color":"000000","profile_use_background_image":false,"profile_image_url":"http:\/\/pbs.twimg.com\/profile_images\/1286087904851185664\/fPSQfS3K_normal.png","profile_image_url_https":"https:\/\/pbs.twimg.com\/profile_images\/1286087904851185664\/fPSQfS3K_normal.png","profile_banner_url":"https:\/\/pbs.twimg.com\/profile_banners\/3058169685\/1595443430","default_profile":false,"default_profile_image":false,"following":null,"follow_request_sent":null,"notifications":null},"geo":null,"coordinates":null,"place":null,"contributors":null,"is_quote_status":false,"quote_count":0,"reply_count":0,"retweet_count":0,"favorite_count":0,"entities":{"hashtags":[],"urls":[],"user_mentions":[{"screen_name":"Louis_Tomlinson","name":"Louis Tomlinson","id":84279963,"id_str":"84279963","indices":[0,16]},{"screen_name":"NiallOfficial","name":"Niall Horan","id":105119490,"id_str":"105119490","indices":[17,31]},{"screen_name":"Harry_Styles","name":"Harry Styles.","id":181561712,"id_str":"181561712","indices":[32,45]},{"screen_name":"LiamPayne","name":"Liam","id":158314798,"id_str":"158314798","indices":[46,56]},{"screen_name":"zaynmalik","name":"zayn","id":176566242,"id_str":"176566242","indices":[57,67]}],"symbols":[]},"favorited":false,"retweeted":false,"filter_level":"low","lang":"en","timestamp_ms":"1595503494665"}
