{"created_at":"Thu Jul 23 10:37:53 +0000 2020","id":1286249168009216001,"id_str":"1286249168009216001","text":"RT @syddks: \uc820\ub4dd\uc774 \uc2a4\uafb8 \ub108\ubb34 \uc798\ud558\ub294\uac70 \uc544\ub2c8\ub0d0\uace0; \ubbf8\ucce4\ub2e4 \uc5b4\uca5c \uc774\ub807\uac8c \uc798\uafb8\ubbf8\uc9c0...? \uc2a4\uafb8 \uc7a5\uc778 \uae40\uc81c\ub2c8 \uadfc\ub370 \uc544\uc774\uc2a4\ud06c\ub9bc \uc2a4\ud2f0\ucee4 \uc800\uac70 \uc2a4\ud3ec \uc544\ub2c8\ub0d0     \n\n#BLACKPINK #JENNIE #\uc81c\ub2c8 https:\/\/t.co\/TNTxwfeVn5","source":"\u003ca href=\"https:\/\/mobile.twitter.com\" rel=\"nofollow\"\u003eTwitter Web App\u003c\/a\u003e","truncated":false,"in_reply_to_status_id":null,"in_reply_to_status_id_str":null,"in_reply_to_user_id":null,"in_reply_to_user_id_str":null,"in_reply_to_screen_name":null,"user":{"id":1244873961961209856,"id_str":"1244873961961209856","name":"Esther","screen_name":"Estherclaire27","location":null,"url":null,"description":"\ud83d\udc15\ud83d\udc16\n*LOOK UP IN THE SKY IT'S A \"B\"IRD IT'S A \"P\"LANE*","translator_type":"none","protected":false,"verified":false,"followers_count":3,"friends_count":7,"listed_count":0,"favourites_count":2641,"statuses_count":612,"created_at":"Tue Mar 31 06:27:44 +0000 2020","utc_offset":null,"time_zone":null,"geo_enabled":false,"lang":null,"contributors_enabled":false,"is_translator":false,"profile_background_color":"F5F8FA","profile_background_image_url":"","profile_background_image_url_https":"","profile_background_tile":false,"profile_link_color":"1DA1F2","profile_sidebar_border_color":"C0DEED","profile_sidebar_fill_color":"DDEEF6","profile_text_color":"333333","profile_use_background_image":true,"profile_image_url":"http:\/\/pbs.twimg.com\/profile_images\/1265065452260061184\/NFMhNq6s_normal.jpg","profile_image_url_https":"https:\/\/pbs.twimg.com\/profile_images\/1265065452260061184\/NFMhNq6s_normal.jpg","profile_banner_url":"https:\/\/pbs.twimg.com\/profile_banners\/1244873961961209856\/1586919421","default_profile":true,"default_profile_image":false,"following":null,"follow_request_sent":null,"notifications":null},"geo":null,"coordinates":null,"place":null,"contributors":null,"retweeted_status":{"created_at":"Thu Jul 23 01:31:01 +0000 2020","id":1286111544439275522,"id_str":"1286111544439275522","text":"\uc820\ub4dd\uc774 \uc2a4\uafb8 \ub108\ubb34 \uc798\ud558\ub294\uac70 \uc544\ub2c8\ub0d0\uace0; \ubbf8\ucce4\ub2e4 \uc5b4\uca5c \uc774\ub807\uac8c \uc798\uafb8\ubbf8\uc9c0...? \uc2a4\uafb8 \uc7a5\uc778 \uae40\uc81c\ub2c8 \uadfc\ub370 \uc544\uc774\uc2a4\ud06c\ub9bc \uc2a4\ud2f0\ucee4 \uc800\uac70 \uc2a4\ud3ec \uc544\ub2c8\ub0d0     \n\n#BLACKPINK #JENNIE #\uc81c\ub2c8 https:\/\/t.co\/TNTxwfeVn5","display_text_range":[0,102],"source":"\u003ca href=\"http:\/\/twitter.com\/download\/iphone\" rel=\"nofollow\"\u003eTwitter for iPhone\u003c\/a\u003e","truncated":false,"in_reply_to_status_id":null,"in_reply_to_status_id_str":null,"in_reply_to_user_id":null,"in_reply_to_user_id_str":null,"in_reply_to_screen_name":null,"user":{"id":868863339677368320,"id_str":"868863339677368320","name":"\ub9c8\uc774\ucbb8","screen_name":"syddks","location":null,"url":null,"description":null,"translator_type":"none","protected":false,"verified":false,"followers_count":47,"friends_count":17,"listed_count":0,"favourites_count":0,"statuses_count":8,"created_at":"Sun May 28 16:15:37 +0000 2017","utc_offset":null,"time_zone":null,"geo_enabled":false,"lang":null,"contributors_enabled":false,"is_translator":false,"profile_background_color":"F5F8FA","profile_background_image_url":"","profile_background_image_url_https":"","profile_background_tile":false,"profile_link_color":"1DA1F2","profile_sidebar_border_color":"C0DEED","profile_sidebar_fill_color":"DDEEF6","profile_text_color":"333333","profile_use_background_image":true,"profile_image_url":"http:\/\/pbs.twimg.com\/profile_images\/1278951122497990666\/h2BebL54_normal.jpg","profile_image_url_https":"https:\/\/pbs.twimg.com\/profile_images\/1278951122497990666\/h2BebL54_normal.jpg","default_profile":true,"default_profile_image":false,"following":null,"follow_request_sent":null,"notifications":null},"geo":null,"coordinates":null,"place":null,"contributors":null,"is_quote_status":false,"quote_count":584,"reply_count":144,"retweet_count":3139,"favorite_count":8708,"entities":{"hashtags":[{"text":"BLACKPINK","indices":[80,90]},{"text":"JENNIE","indices":[91,98]},{"text":"\uc81c\ub2c8","indices":[99,102]}],"urls":[],"user_mentions":[],"symbols":[],"media":[{"id":1286111516203208706,"id_str":"1286111516203208706","indices":[103,126],"media_url":"http:\/\/pbs.twimg.com\/media\/EdkvnCDU0AIq4vS.jpg","media_url_https":"https:\/\/pbs.twimg.com\/media\/EdkvnCDU0AIq4vS.jpg","url":"https:\/\/t.co\/TNTxwfeVn5","display_url":"pic.twitter.com\/TNTxwfeVn5","expanded_url":"https:\/\/twitter.com\/syddks\/status\/1286111544439275522\/photo\/1","type":"photo","sizes":{"large":{"w":2048,"h":2048,"resize":"fit"},"thumb":{"w":150,"h":150,"resize":"crop"},"medium":{"w":1200,"h":1200,"resize":"fit"},"small":{"w":680,"h":680,"resize":"fit"}}}]},"extended_entities":{"media":[{"id":1286111516203208706,"id_str":"1286111516203208706","indices":[103,126],"media_url":"http:\/\/pbs.twimg.com\/media\/EdkvnCDU0AIq4vS.jpg","media_url_https":"https:\/\/pbs.twimg.com\/media\/EdkvnCDU0AIq4vS.jpg","url":"https:\/\/t.co\/TNTxwfeVn5","display_url":"pic.twitter.com\/TNTxwfeVn5","expanded_url":"https:\/\/twitter.com\/syddks\/status\/1286111544439275522\/photo\/1","type":"photo","sizes":{"large":{"w":2048,"h":2048,"resize":"fit"},"thumb":{"w":150,"h":150,"resize":"crop"},"medium":{"w":1200,"h":1200,"resize":"fit"},"small":{"w":680,"h":680,"resize":"fit"}}},{"id":1286111516203220992,"id_str":"1286111516203220992","indices":[103,126],"media_url":"http:\/\/pbs.twimg.com\/media\/EdkvnCDVAAAY4da.jpg","media_url_https":"https:\/\/pbs.twimg.com\/media\/EdkvnCDVAAAY4da.jpg","url":"https:\/\/t.co\/TNTxwfeVn5","display_url":"pic.twitter.com\/TNTxwfeVn5","expanded_url":"https:\/\/twitter.com\/syddks\/status\/1286111544439275522\/photo\/1","type":"photo","sizes":{"thumb":{"w":150,"h":150,"resize":"crop"},"small":{"w":680,"h":680,"resize":"fit"},"medium":{"w":1200,"h":1200,"resize":"fit"},"large":{"w":2048,"h":2048,"resize":"fit"}}},{"id":1286111516203204610,"id_str":"1286111516203204610","indices":[103,126],"media_url":"http:\/\/pbs.twimg.com\/media\/EdkvnCDUwAIiHrX.jpg","media_url_https":"https:\/\/pbs.twimg.com\/media\/EdkvnCDUwAIiHrX.jpg","url":"https:\/\/t.co\/TNTxwfeVn5","display_url":"pic.twitter.com\/TNTxwfeVn5","expanded_url":"https:\/\/twitter.com\/syddks\/status\/1286111544439275522\/photo\/1","type":"photo","sizes":{"medium":{"w":1200,"h":1200,"resize":"fit"},"thumb":{"w":150,"h":150,"resize":"crop"},"small":{"w":680,"h":680,"resize":"fit"},"large":{"w":2048,"h":2048,"resize":"fit"}}}]},"favorited":false,"retweeted":false,"possibly_sensitive":false,"filter_level":"low","lang":"ko"},"is_quote_status":false,"quote_count":0,"reply_count":0,"retweet_count":0,"favorite_count":0,"entities":{"hashtags":[{"text":"BLACKPINK","indices":[92,102]},{"text":"JENNIE","indices":[103,110]},{"text":"\uc81c\ub2c8","indices":[111,114]}],"urls":[],"user_mentions":[{"screen_name":"syddks","name":"\ub9c8\uc774\ucbb8","id":868863339677368320,"id_str":"868863339677368320","indices":[3,10]}],"symbols":[],"media":[{"id":1286111516203208706,"id_str":"1286111516203208706","indices":[115,138],"media_url":"http:\/\/pbs.twimg.com\/media\/EdkvnCDU0AIq4vS.jpg","media_url_https":"https:\/\/pbs.twimg.com\/media\/EdkvnCDU0AIq4vS.jpg","url":"https:\/\/t.co\/TNTxwfeVn5","display_url":"pic.twitter.com\/TNTxwfeVn5","expanded_url":"https:\/\/twitter.com\/syddks\/status\/1286111544439275522\/photo\/1","type":"photo","sizes":{"large":{"w":2048,"h":2048,"resize":"fit"},"thumb":{"w":150,"h":150,"resize":"crop"},"medium":{"w":1200,"h":1200,"resize":"fit"},"small":{"w":680,"h":680,"resize":"fit"}},"source_status_id":1286111544439275522,"source_status_id_str":"1286111544439275522","source_user_id":868863339677368320,"source_user_id_str":"868863339677368320"}]},"extended_entities":{"media":[{"id":1286111516203208706,"id_str":"1286111516203208706","indices":[115,138],"media_url":"http:\/\/pbs.twimg.com\/media\/EdkvnCDU0AIq4vS.jpg","media_url_https":"https:\/\/pbs.twimg.com\/media\/EdkvnCDU0AIq4vS.jpg","url":"https:\/\/t.co\/TNTxwfeVn5","display_url":"pic.twitter.com\/TNTxwfeVn5","expanded_url":"https:\/\/twitter.com\/syddks\/status\/1286111544439275522\/photo\/1","type":"photo","sizes":{"large":{"w":2048,"h":2048,"resize":"fit"},"thumb":{"w":150,"h":150,"resize":"crop"},"medium":{"w":1200,"h":1200,"resize":"fit"},"small":{"w":680,"h":680,"resize":"fit"}},"source_status_id":1286111544439275522,"source_status_id_str":"1286111544439275522","source_user_id":868863339677368320,"source_user_id_str":"868863339677368320"},{"id":1286111516203220992,"id_str":"1286111516203220992","indices":[115,138],"media_url":"http:\/\/pbs.twimg.com\/media\/EdkvnCDVAAAY4da.jpg","media_url_https":"https:\/\/pbs.twimg.com\/media\/EdkvnCDVAAAY4da.jpg","url":"https:\/\/t.co\/TNTxwfeVn5","display_url":"pic.twitter.com\/TNTxwfeVn5","expanded_url":"https:\/\/twitter.com\/syddks\/status\/1286111544439275522\/photo\/1","type":"photo","sizes":{"thumb":{"w":150,"h":150,"resize":"crop"},"small":{"w":680,"h":680,"resize":"fit"},"medium":{"w":1200,"h":1200,"resize":"fit"},"large":{"w":2048,"h":2048,"resize":"fit"}},"source_status_id":1286111544439275522,"source_status_id_str":"1286111544439275522","source_user_id":868863339677368320,"source_user_id_str":"868863339677368320"},{"id":1286111516203204610,"id_str":"1286111516203204610","indices":[115,138],"media_url":"http:\/\/pbs.twimg.com\/media\/EdkvnCDUwAIiHrX.jpg","media_url_https":"https:\/\/pbs.twimg.com\/media\/EdkvnCDUwAIiHrX.jpg","url":"https:\/\/t.co\/TNTxwfeVn5","display_url":"pic.twitter.com\/TNTxwfeVn5","expanded_url":"https:\/\/twitter.com\/syddks\/status\/1286111544439275522\/photo\/1","type":"photo","sizes":{"medium":{"w":1200,"h":1200,"resize":"fit"},"thumb":{"w":150,"h":150,"resize":"crop"},"small":{"w":680,"h":680,"resize":"fit"},"large":{"w":2048,"h":2048,"resize":"fit"}},"source_status_id":1286111544439275522,"source_status_id_str":"1286111544439275522","source_user_id":868863339677368320,"source_user_id_str":"868863339677368320"}]},"favorited":false,"retweeted":false,"possibly_sensitive":false,"filter_level":"low","lang":"ko","timestamp_ms":"1595500673664"}
