{"created_at":"Thu Jul 23 10:37:06 +0000 2020","id":1286248970885324806,"id_str":"1286248970885324806","text":"RT @gvprakash: \ud83d\udd25\ud83d\udd25 #vaadivaasal #\u0bb5\u0bbe\u0b9f\u0bbf\u0bb5\u0bbe\u0b9a\u0bb2\u0bcd ...  Character design poster from #teamvaadivaasal on his birthday  #happybirthdaySuriya ... #GV7\u2026","source":"\u003ca href=\"http:\/\/twitter.com\/download\/android\" rel=\"nofollow\"\u003eTwitter for Android\u003c\/a\u003e","truncated":false,"in_reply_to_status_id":null,"in_reply_to_status_id_str":null,"in_reply_to_user_id":null,"in_reply_to_user_id_str":null,"in_reply_to_screen_name":null,"user":{"id":1152401535097196544,"id_str":"1152401535097196544","name":"Shri Ram","screen_name":"ShriRam04529850","location":null,"url":null,"description":null,"translator_type":"none","protected":false,"verified":false,"followers_count":22,"friends_count":166,"listed_count":0,"favourites_count":1331,"statuses_count":2048,"created_at":"Sat Jul 20 02:15:11 +0000 2019","utc_offset":null,"time_zone":null,"geo_enabled":false,"lang":null,"contributors_enabled":false,"is_translator":false,"profile_background_color":"F5F8FA","profile_background_image_url":"","profile_background_image_url_https":"","profile_background_tile":false,"profile_link_color":"1DA1F2","profile_sidebar_border_color":"C0DEED","profile_sidebar_fill_color":"DDEEF6","profile_text_color":"333333","profile_use_background_image":true,"profile_image_url":"http:\/\/pbs.twimg.com\/profile_images\/1281931893223550976\/2nPDPQcJ_normal.jpg","profile_image_url_https":"https:\/\/pbs.twimg.com\/profile_images\/1281931893223550976\/2nPDPQcJ_normal.jpg","default_profile":true,"default_profile_image":false,"following":null,"follow_request_sent":null,"notifications":null},"geo":null,"coordinates":null,"place":null,"contributors":null,"retweeted_status":{"created_at":"Thu Jul 23 06:35:04 +0000 2020","id":1286188059856232448,"id_str":"1286188059856232448","text":"\ud83d\udd25\ud83d\udd25 #vaadivaasal #\u0bb5\u0bbe\u0b9f\u0bbf\u0bb5\u0bbe\u0b9a\u0bb2\u0bcd ...  Character design poster from #teamvaadivaasal on his birthday  #happybirthdaySuriya\u2026 https:\/\/t.co\/xjadg1fWBO","display_text_range":[0,140],"source":"\u003ca href=\"http:\/\/twitter.com\/download\/iphone\" rel=\"nofollow\"\u003eTwitter for iPhone\u003c\/a\u003e","truncated":true,"in_reply_to_status_id":null,"in_reply_to_status_id_str":null,"in_reply_to_user_id":null,"in_reply_to_user_id_str":null,"in_reply_to_screen_name":null,"user":{"id":106485105,"id_str":"106485105","name":"G.V.Prakash Kumar","screen_name":"gvprakash","location":"india","url":"http:\/\/bit.ly\/GVPyoutube","description":"\ud83d\udcab\u2728Fly High\u2728\ud83d\udcab http:\/\/Instagram.com\/gvprakash","translator_type":"none","protected":false,"verified":true,"followers_count":5671487,"friends_count":70,"listed_count":989,"favourites_count":45918,"statuses_count":15144,"created_at":"Tue Jan 19 18:25:08 +0000 2010","utc_offset":null,"time_zone":null,"geo_enabled":true,"lang":null,"contributors_enabled":false,"is_translator":false,"profile_background_color":"000000","profile_background_image_url":"http:\/\/abs.twimg.com\/images\/themes\/theme14\/bg.gif","profile_background_image_url_https":"https:\/\/abs.twimg.com\/images\/themes\/theme14\/bg.gif","profile_background_tile":false,"profile_link_color":"3C4D0B","profile_sidebar_border_color":"000000","profile_sidebar_fill_color":"000000","profile_text_color":"FFFFFF","profile_use_background_image":true,"profile_image_url":"http:\/\/pbs.twimg.com\/profile_images\/1282684874076250113\/bRncfJ8X_normal.jpg","profile_image_url_https":"https:\/\/pbs.twimg.com\/profile_images\/1282684874076250113\/bRncfJ8X_normal.jpg","profile_banner_url":"https:\/\/pbs.twimg.com\/profile_banners\/106485105\/1594737293","default_profile":false,"default_profile_image":false,"following":null,"follow_request_sent":null,"notifications":null},"geo":null,"coordinates":null,"place":null,"contributors":null,"is_quote_status":false,"extended_tweet":{"full_text":"\ud83d\udd25\ud83d\udd25 #vaadivaasal #\u0bb5\u0bbe\u0b9f\u0bbf\u0bb5\u0bbe\u0b9a\u0bb2\u0bcd ...  Character design poster from #teamvaadivaasal on his birthday  #happybirthdaySuriya ... #GV75 @Suriya_offl @VetriMaaran @theVcreations @rajsekarpandian https:\/\/t.co\/nGDc70UiY9","display_text_range":[0,183],"entities":{"hashtags":[{"text":"vaadivaasal","indices":[3,15]},{"text":"\u0bb5\u0bbe\u0b9f\u0bbf\u0bb5\u0bbe\u0b9a\u0bb2\u0bcd","indices":[16,26]},{"text":"teamvaadivaasal","indices":[61,77]},{"text":"happybirthdaySuriya","indices":[95,115]},{"text":"GV75","indices":[120,125]}],"urls":[],"user_mentions":[{"screen_name":"Suriya_offl","name":"Suriya Sivakumar","id":3065261233,"id_str":"3065261233","indices":[126,138]},{"screen_name":"VetriMaaran","name":"Vetri Maaran","id":100775570,"id_str":"100775570","indices":[139,151]},{"screen_name":"theVcreations","name":"Kalaippuli S Thanu","id":2237603617,"id_str":"2237603617","indices":[152,166]},{"screen_name":"rajsekarpandian","name":"Rajsekar Pandian","id":1718546557,"id_str":"1718546557","indices":[167,183]}],"symbols":[],"media":[{"id":1286188049680879616,"id_str":"1286188049680879616","indices":[184,207],"media_url":"http:\/\/pbs.twimg.com\/media\/Edl1N3eU0AAHc13.jpg","media_url_https":"https:\/\/pbs.twimg.com\/media\/Edl1N3eU0AAHc13.jpg","url":"https:\/\/t.co\/nGDc70UiY9","display_url":"pic.twitter.com\/nGDc70UiY9","expanded_url":"https:\/\/twitter.com\/gvprakash\/status\/1286188059856232448\/photo\/1","type":"photo","sizes":{"small":{"w":435,"h":680,"resize":"fit"},"thumb":{"w":150,"h":150,"resize":"crop"},"medium":{"w":768,"h":1200,"resize":"fit"},"large":{"w":1310,"h":2048,"resize":"fit"}}}]},"extended_entities":{"media":[{"id":1286188049680879616,"id_str":"1286188049680879616","indices":[184,207],"media_url":"http:\/\/pbs.twimg.com\/media\/Edl1N3eU0AAHc13.jpg","media_url_https":"https:\/\/pbs.twimg.com\/media\/Edl1N3eU0AAHc13.jpg","url":"https:\/\/t.co\/nGDc70UiY9","display_url":"pic.twitter.com\/nGDc70UiY9","expanded_url":"https:\/\/twitter.com\/gvprakash\/status\/1286188059856232448\/photo\/1","type":"photo","sizes":{"small":{"w":435,"h":680,"resize":"fit"},"thumb":{"w":150,"h":150,"resize":"crop"},"medium":{"w":768,"h":1200,"resize":"fit"},"large":{"w":1310,"h":2048,"resize":"fit"}}}]}},"quote_count":213,"reply_count":353,"retweet_count":7408,"favorite_count":21063,"entities":{"hashtags":[{"text":"vaadivaasal","indices":[3,15]},{"text":"\u0bb5\u0bbe\u0b9f\u0bbf\u0bb5\u0bbe\u0b9a\u0bb2\u0bcd","indices":[16,26]},{"text":"teamvaadivaasal","indices":[61,77]},{"text":"happybirthdaySuriya","indices":[95,115]}],"urls":[{"url":"https:\/\/t.co\/xjadg1fWBO","expanded_url":"https:\/\/twitter.com\/i\/web\/status\/1286188059856232448","display_url":"twitter.com\/i\/web\/status\/1\u2026","indices":[117,140]}],"user_mentions":[],"symbols":[]},"favorited":false,"retweeted":false,"possibly_sensitive":false,"filter_level":"low","lang":"en"},"is_quote_status":false,"quote_count":0,"reply_count":0,"retweet_count":0,"favorite_count":0,"entities":{"hashtags":[{"text":"vaadivaasal","indices":[18,30]},{"text":"\u0bb5\u0bbe\u0b9f\u0bbf\u0bb5\u0bbe\u0b9a\u0bb2\u0bcd","indices":[31,41]},{"text":"teamvaadivaasal","indices":[76,92]},{"text":"happybirthdaySuriya","indices":[110,130]}],"urls":[],"user_mentions":[{"screen_name":"gvprakash","name":"G.V.Prakash Kumar","id":106485105,"id_str":"106485105","indices":[3,13]}],"symbols":[]},"favorited":false,"retweeted":false,"filter_level":"low","lang":"en","timestamp_ms":"1595500626666"}
