{"created_at":"Thu Jul 23 11:13:44 +0000 2020","id":1286258189927723008,"id_str":"1286258189927723008","text":"RT @Hindu_putr: \u0906\u0913 \u092e\u093f\u0932\u0915\u0930 \u0915\u0930\u0947\u0902 \u0938\u093e\u0927\u0928\u093e, \u0926\u093f\u0935\u094d\u092f \u0936\u0915\u094d\u0924\u093f \u0915\u0947 \u0924\u0902\u0924\u094d\u0930 \u0915\u0940,\n\u0917\u0942\u0901\u091c\u0947 \u092b\u093f\u0930 \u091c\u092f\u0915\u093e\u0930 \u0927\u0930\u093e \u092a\u0930, \u0938\u0924\u094d\u092f \u0938\u0928\u093e\u0924\u0928 \u0927\u0930\u094d\u092e \u0915\u0940 \u0964\ud83d\udea9\ud83d\udea9\n#\u091c\u093e\u0924\u093f\u0935\u093e\u0926_\u0935\u093f\u0937_\u0939\u093f\u0902\u0926\u0941\u0924\u094d\u0935_\u0905\u092e\u0943\u0924\n#\u091c\u093e\u2026","source":"\u003ca href=\"http:\/\/twitter.com\/download\/android\" rel=\"nofollow\"\u003eTwitter for Android\u003c\/a\u003e","truncated":false,"in_reply_to_status_id":null,"in_reply_to_status_id_str":null,"in_reply_to_user_id":null,"in_reply_to_user_id_str":null,"in_reply_to_screen_name":null,"user":{"id":2890900471,"id_str":"2890900471","name":"\u0938\u0941\u0928\u093f\u0932 \u0909\u092a\u093e\u0927\u094d\u092f\u093e\u092f","screen_name":"SuSunil777","location":"Rajasthan, India","url":null,"description":null,"translator_type":"none","protected":false,"verified":false,"followers_count":1301,"friends_count":3182,"listed_count":0,"favourites_count":7174,"statuses_count":4359,"created_at":"Wed Nov 05 14:12:04 +0000 2014","utc_offset":null,"time_zone":null,"geo_enabled":false,"lang":null,"contributors_enabled":false,"is_translator":false,"profile_background_color":"C0DEED","profile_background_image_url":"http:\/\/abs.twimg.com\/images\/themes\/theme1\/bg.png","profile_background_image_url_https":"https:\/\/abs.twimg.com\/images\/themes\/theme1\/bg.png","profile_background_tile":false,"profile_link_color":"1DA1F2","profile_sidebar_border_color":"C0DEED","profile_sidebar_fill_color":"DDEEF6","profile_text_color":"333333","profile_use_background_image":true,"profile_image_url":"http:\/\/pbs.twimg.com\/profile_images\/1249745800944484360\/NKp2UfGq_normal.jpg","profile_image_url_https":"https:\/\/pbs.twimg.com\/profile_images\/1249745800944484360\/NKp2UfGq_normal.jpg","profile_banner_url":"https:\/\/pbs.twimg.com\/profile_banners\/2890900471\/1586524407","default_profile":true,"default_profile_image":false,"following":null,"follow_request_sent":null,"notifications":null},"geo":null,"coordinates":null,"place":null,"contributors":null,"retweeted_status":{"created_at":"Thu Jul 23 11:08:53 +0000 2020","id":1286256968957485057,"id_str":"1286256968957485057","text":"\u0906\u0913 \u092e\u093f\u0932\u0915\u0930 \u0915\u0930\u0947\u0902 \u0938\u093e\u0927\u0928\u093e, \u0926\u093f\u0935\u094d\u092f \u0936\u0915\u094d\u0924\u093f \u0915\u0947 \u0924\u0902\u0924\u094d\u0930 \u0915\u0940,\n\u0917\u0942\u0901\u091c\u0947 \u092b\u093f\u0930 \u091c\u092f\u0915\u093e\u0930 \u0927\u0930\u093e \u092a\u0930, \u0938\u0924\u094d\u092f \u0938\u0928\u093e\u0924\u0928 \u0927\u0930\u094d\u092e \u0915\u0940 \u0964\ud83d\udea9\ud83d\udea9\u2026 https:\/\/t.co\/0F7Th8fG21","source":"\u003ca href=\"http:\/\/twitter.com\/download\/android\" rel=\"nofollow\"\u003eTwitter for Android\u003c\/a\u003e","truncated":true,"in_reply_to_status_id":null,"in_reply_to_status_id_str":null,"in_reply_to_user_id":null,"in_reply_to_user_id_str":null,"in_reply_to_screen_name":null,"user":{"id":1105738634286776320,"id_str":"1105738634286776320","name":"Gopal Sharma","screen_name":"Hindu_putr","location":"Jehanabad, India","url":"http:\/\/facebook.com\/Gopal-Kumar-2038141453116719\/","description":"Co-convener-IT Cell&Social Media-dist-@bjp4india (ek roti team Members), \n\u092e\u0948\u0902 \u0930\u0939\u0942 \u092f\u093e \u0928 \u0930\u0939\u0942 \u0926\u0947\u0936 \u0930\u0939\u0928\u093e \u091a\u093e\u0939\u093f\u090f            \u007bNation first\u007d","translator_type":"none","protected":false,"verified":false,"followers_count":3060,"friends_count":3431,"listed_count":0,"favourites_count":872,"statuses_count":2616,"created_at":"Wed Mar 13 07:53:28 +0000 2019","utc_offset":null,"time_zone":null,"geo_enabled":true,"lang":null,"contributors_enabled":false,"is_translator":false,"profile_background_color":"F5F8FA","profile_background_image_url":"","profile_background_image_url_https":"","profile_background_tile":false,"profile_link_color":"1DA1F2","profile_sidebar_border_color":"C0DEED","profile_sidebar_fill_color":"DDEEF6","profile_text_color":"333333","profile_use_background_image":true,"profile_image_url":"http:\/\/pbs.twimg.com\/profile_images\/1282167697321517056\/Fby9meNg_normal.jpg","profile_image_url_https":"https:\/\/pbs.twimg.com\/profile_images\/1282167697321517056\/Fby9meNg_normal.jpg","profile_banner_url":"https:\/\/pbs.twimg.com\/profile_banners\/1105738634286776320\/1593832164","default_profile":true,"default_profile_image":false,"following":null,"follow_request_sent":null,"notifications":null},"geo":null,"coordinates":null,"place":null,"contributors":null,"is_quote_status":false,"extended_tweet":{"full_text":"\u0906\u0913 \u092e\u093f\u0932\u0915\u0930 \u0915\u0930\u0947\u0902 \u0938\u093e\u0927\u0928\u093e, \u0926\u093f\u0935\u094d\u092f \u0936\u0915\u094d\u0924\u093f \u0915\u0947 \u0924\u0902\u0924\u094d\u0930 \u0915\u0940,\n\u0917\u0942\u0901\u091c\u0947 \u092b\u093f\u0930 \u091c\u092f\u0915\u093e\u0930 \u0927\u0930\u093e \u092a\u0930, \u0938\u0924\u094d\u092f \u0938\u0928\u093e\u0924\u0928 \u0927\u0930\u094d\u092e \u0915\u0940 \u0964\ud83d\udea9\ud83d\udea9\n#\u091c\u093e\u0924\u093f\u0935\u093e\u0926_\u0935\u093f\u0937_\u0939\u093f\u0902\u0926\u0941\u0924\u094d\u0935_\u0905\u092e\u0943\u0924\n#\u091c\u093e\u0924\u093f\u0935\u093e\u0926_\u0935\u093f\u0937_\u0939\u093f\u0902\u0926\u0941\u0924\u094d\u0935_\u0905\u092e\u0943\u0924\n\n@Brand_Anuj @beingarun28\n@Sudhir_mishr @rashmivar\n@RealShakunimama @manishmbjp","display_text_range":[0,226],"entities":{"hashtags":[{"text":"\u091c\u093e\u0924\u093f\u0935\u093e\u0926_\u0935\u093f\u0937_\u0939\u093f\u0902\u0926\u0941\u0924\u094d\u0935_\u0905\u092e\u0943\u0924","indices":[93,119]},{"text":"\u091c\u093e\u0924\u093f\u0935\u093e\u0926_\u0935\u093f\u0937_\u0939\u093f\u0902\u0926\u0941\u0924\u094d\u0935_\u0905\u092e\u0943\u0924","indices":[120,146]}],"urls":[],"user_mentions":[{"screen_name":"Brand_Anuj","name":"Brand Anuj \u265b","id":1252920567033987073,"id_str":"1252920567033987073","indices":[148,159]},{"screen_name":"beingarun28","name":"Arun Yadav","id":3319971199,"id_str":"3319971199","indices":[160,172]},{"screen_name":"Sudhir_mishr","name":"Sudhir Mishra","id":945615093638733824,"id_str":"945615093638733824","indices":[173,186]},{"screen_name":"rashmivar","name":"\u0930\u0936\u094d\u092e\u093f \u0936\u0930\u094d\u092e\u093e","id":1246812524470661125,"id_str":"1246812524470661125","indices":[187,197]},{"screen_name":"RealShakunimama","name":"\u0936\u0915\u0940\u0932\u093e \u092c\u093e\u0928\u094b (\u092a\u0915\u094d\u0915\u093e \u0908\u092e\u093e\u0928) - TSM","id":1239618990189596679,"id_str":"1239618990189596679","indices":[198,214]},{"screen_name":"manishmbjp","name":"\u092e\u0928\u0940\u0937 \u092e\u093f\u0936\u094d\u0930\u093e","id":1180389641775542272,"id_str":"1180389641775542272","indices":[215,226]}],"symbols":[]}},"quote_count":0,"reply_count":0,"retweet_count":2,"favorite_count":2,"entities":{"hashtags":[],"urls":[{"url":"https:\/\/t.co\/0F7Th8fG21","expanded_url":"https:\/\/twitter.com\/i\/web\/status\/1286256968957485057","display_url":"twitter.com\/i\/web\/status\/1\u2026","indices":[94,117]}],"user_mentions":[],"symbols":[]},"favorited":false,"retweeted":false,"filter_level":"low","lang":"hi"},"is_quote_status":false,"quote_count":0,"reply_count":0,"retweet_count":0,"favorite_count":0,"entities":{"hashtags":[{"text":"\u091c\u093e\u0924\u093f\u0935\u093e\u0926_\u0935\u093f\u0937_\u0939\u093f\u0902\u0926\u0941\u0924\u094d\u0935_\u0905\u092e\u0943\u0924","indices":[109,135]}],"urls":[],"user_mentions":[{"screen_name":"Hindu_putr","name":"Gopal Sharma","id":1105738634286776320,"id_str":"1105738634286776320","indices":[3,14]}],"symbols":[]},"favorited":false,"retweeted":false,"filter_level":"low","lang":"hi","timestamp_ms":"1595502824657"}
