{"created_at":"Thu Jul 23 10:37:53 +0000 2020","id":1286249167984066561,"id_str":"1286249167984066561","text":"Ki\u1ebfm ti\u1ec1n mi\u1ec5n ph\u00ed, n\u1ea1p h\u00f3a \u0111\u01a1n \u0111i\u1ec7n tho\u1ea1i ho\u1eb7c n\u1ea1p th\u1ebb Garena. Phi\u00ean b\u1ea3n ti\u1ebfng Vi\u1ec7t c\u1ee7a '\u0110\u1ed3ng b\u00e1o', c\u1ee7a Cashzine c\u2026 https:\/\/t.co\/GXl213LtDg","display_text_range":[0,140],"source":"\u003ca href=\"http:\/\/twitter.com\/download\/android\" rel=\"nofollow\"\u003eTwitter for Android\u003c\/a\u003e","truncated":true,"in_reply_to_status_id":null,"in_reply_to_status_id_str":null,"in_reply_to_user_id":null,"in_reply_to_user_id_str":null,"in_reply_to_screen_name":null,"user":{"id":1286096945795104768,"id_str":"1286096945795104768","name":"Tr\u1ea7n Th\u1ecb Thu\u1ef7","screen_name":"TrnThTh12233314","location":null,"url":null,"description":"Ti\u1ec3u s\u1eed g\u1ecdi t\u00ean tao v\u00e0 b\u1ea1n th\u00e2n nh\u1ea5t l\u00e0 B\u00edch","translator_type":"none","protected":false,"verified":false,"followers_count":0,"friends_count":6,"listed_count":0,"favourites_count":2,"statuses_count":3,"created_at":"Thu Jul 23 00:33:50 +0000 2020","utc_offset":null,"time_zone":null,"geo_enabled":false,"lang":null,"contributors_enabled":false,"is_translator":false,"profile_background_color":"F5F8FA","profile_background_image_url":"","profile_background_image_url_https":"","profile_background_tile":false,"profile_link_color":"1DA1F2","profile_sidebar_border_color":"C0DEED","profile_sidebar_fill_color":"DDEEF6","profile_text_color":"333333","profile_use_background_image":true,"profile_image_url":"http:\/\/pbs.twimg.com\/profile_images\/1286097377518968833\/8_6mLLxQ_normal.jpg","profile_image_url_https":"https:\/\/pbs.twimg.com\/profile_images\/1286097377518968833\/8_6mLLxQ_normal.jpg","default_profile":true,"default_profile_image":false,"following":null,"follow_request_sent":null,"notifications":null},"geo":null,"coordinates":null,"place":null,"contributors":null,"is_quote_status":false,"extended_tweet":{"full_text":"Ki\u1ebfm ti\u1ec1n mi\u1ec5n ph\u00ed, n\u1ea1p h\u00f3a \u0111\u01a1n \u0111i\u1ec7n tho\u1ea1i ho\u1eb7c n\u1ea1p th\u1ebb Garena. Phi\u00ean b\u1ea3n ti\u1ebfng Vi\u1ec7t c\u1ee7a '\u0110\u1ed3ng b\u00e1o', c\u1ee7a Cashzine c\u00f3 tr\u1ea3i nghi\u1ec7m t\u1ed1t v\u1edbi c\u00e1c video th\u00fa v\u1ecb v\u00e0 ki\u1ebfm \u0111\u01b0\u1ee3c nhi\u1ec1u thu nh\u1eadp . Nh\u1eadp m\u00e3 c\u1ee7a t\u00f4i:16621289, b\u1ea1n c\u00f3 th\u1ec3 nh\u1eadn \u0111\u01b0\u1ee3c 8000 xu https:\/\/t.co\/lghufSeTLF","display_text_range":[0,238],"entities":{"hashtags":[],"urls":[],"user_mentions":[],"symbols":[],"media":[{"id":1286249155698909184,"id_str":"1286249155698909184","indices":[239,262],"description":"Fawn Cartoon GIF","media_url":"http:\/\/pbs.twimg.com\/tweet_video_thumb\/EdmsytIUYAAsmJn.jpg","media_url_https":"https:\/\/pbs.twimg.com\/tweet_video_thumb\/EdmsytIUYAAsmJn.jpg","url":"https:\/\/t.co\/lghufSeTLF","display_url":"pic.twitter.com\/lghufSeTLF","expanded_url":"https:\/\/twitter.com\/TrnThTh12233314\/status\/1286249167984066561\/photo\/1","type":"animated_gif","video_info":{"aspect_ratio":[83,81],"variants":[{"bitrate":0,"content_type":"video\/mp4","url":"https:\/\/video.twimg.com\/tweet_video\/EdmsytIUYAAsmJn.mp4"}]},"sizes":{"thumb":{"w":150,"h":150,"resize":"crop"},"large":{"w":498,"h":486,"resize":"fit"},"small":{"w":498,"h":486,"resize":"fit"},"medium":{"w":498,"h":486,"resize":"fit"}}}]},"extended_entities":{"media":[{"id":1286249155698909184,"id_str":"1286249155698909184","indices":[239,262],"description":"Fawn Cartoon GIF","media_url":"http:\/\/pbs.twimg.com\/tweet_video_thumb\/EdmsytIUYAAsmJn.jpg","media_url_https":"https:\/\/pbs.twimg.com\/tweet_video_thumb\/EdmsytIUYAAsmJn.jpg","url":"https:\/\/t.co\/lghufSeTLF","display_url":"pic.twitter.com\/lghufSeTLF","expanded_url":"https:\/\/twitter.com\/TrnThTh12233314\/status\/1286249167984066561\/photo\/1","type":"animated_gif","video_info":{"aspect_ratio":[83,81],"variants":[{"bitrate":0,"content_type":"video\/mp4","url":"https:\/\/video.twimg.com\/tweet_video\/EdmsytIUYAAsmJn.mp4"}]},"sizes":{"thumb":{"w":150,"h":150,"resize":"crop"},"large":{"w":498,"h":486,"resize":"fit"},"small":{"w":498,"h":486,"resize":"fit"},"medium":{"w":498,"h":486,"resize":"fit"}}}]}},"quote_count":0,"reply_count":0,"retweet_count":0,"favorite_count":0,"entities":{"hashtags":[],"urls":[{"url":"https:\/\/t.co\/GXl213LtDg","expanded_url":"https:\/\/twitter.com\/i\/web\/status\/1286249167984066561","display_url":"twitter.com\/i\/web\/status\/1\u2026","indices":[117,140]}],"user_mentions":[],"symbols":[]},"favorited":false,"retweeted":false,"possibly_sensitive":false,"filter_level":"low","lang":"vi","timestamp_ms":"1595500673658"}
