{"created_at":"Thu Jul 23 10:37:42 +0000 2020","id":1286249121867796481,"id_str":"1286249121867796481","text":"@Mr_Anane_ @Tiishabentil Which type of storm?","display_text_range":[25,45],"source":"\u003ca href=\"http:\/\/twitter.com\/download\/iphone\" rel=\"nofollow\"\u003eTwitter for iPhone\u003c\/a\u003e","truncated":false,"in_reply_to_status_id":1286248532232503296,"in_reply_to_status_id_str":"1286248532232503296","in_reply_to_user_id":46374076,"in_reply_to_user_id_str":"46374076","in_reply_to_screen_name":"Mr_Anane_","user":{"id":2755256422,"id_str":"2755256422","name":"\u00a1\u00a1 Canz \u00a1\u00a1 \ud83c\uddec\ud83c\udded","screen_name":"canz2014","location":"Accra","url":"http:\/\/ghlink.com","description":"let\u2019s rise for a better Ghana \ud83c\uddec\ud83c\udded! Anything food, just invite me and I\u2019ll be there. Backup ac @Canz_2020","translator_type":"none","protected":false,"verified":false,"followers_count":2450,"friends_count":2405,"listed_count":1,"favourites_count":3417,"statuses_count":9639,"created_at":"Fri Aug 29 23:39:08 +0000 2014","utc_offset":null,"time_zone":null,"geo_enabled":false,"lang":null,"contributors_enabled":false,"is_translator":false,"profile_background_color":"C0DEED","profile_background_image_url":"http:\/\/abs.twimg.com\/images\/themes\/theme1\/bg.png","profile_background_image_url_https":"https:\/\/abs.twimg.com\/images\/themes\/theme1\/bg.png","profile_background_tile":false,"profile_link_color":"1DA1F2","profile_sidebar_border_color":"C0DEED","profile_sidebar_fill_color":"DDEEF6","profile_text_color":"333333","profile_use_background_image":true,"profile_image_url":"http:\/\/pbs.twimg.com\/profile_images\/1254541237970968583\/HGFIm_eZ_normal.jpg","profile_image_url_https":"https:\/\/pbs.twimg.com\/profile_images\/1254541237970968583\/HGFIm_eZ_normal.jpg","profile_banner_url":"https:\/\/pbs.twimg.com\/profile_banners\/2755256422\/1575985346","default_profile":true,"default_profile_image":false,"following":null,"follow_request_sent":null,"notifications":null},"geo":null,"coordinates":null,"place":null,"contributors":null,"is_quote_status":false,"quote_count":0,"reply_count":0,"retweet_count":0,"favorite_count":0,"entities":{"hashtags":[],"urls":[],"user_mentions":[{"screen_name":"Mr_Anane_","name":"Kojo Prempeh \ud83d\udc64\ud83d\udc68\ud83c\udffd\u200d\ud83d\udcbb","id":46374076,"id_str":"46374076","indices":[0,10]},{"screen_name":"Tiishabentil","name":"Tiisha","id":1276870513244155904,"id_str":"1276870513244155904","indices":[11,24]}],"symbols":[]},"favorited":false,"retweeted":false,"filter_level":"low","lang":"en","timestamp_ms":"1595500662663"}
