{"created_at":"Thu Jul 23 11:13:39 +0000 2020","id":1286258168956428289,"id_str":"1286258168956428289","text":"@HajerAfrit \u0644\u0645\u0631\u0629 \u0647\u0630\u064a \u0631\u0643\u0632\u062a \u0645\u0644\u064a\u062d \u0648 \u0635\u0648\u062a\u062a \u0644\u0631\u0648\u062d\u064a \ud83e\udd23\ud83e\udd23\ud83e\udd23\ud83e\udd23","display_text_range":[12,48],"source":"\u003ca href=\"http:\/\/twitter.com\/download\/android\" rel=\"nofollow\"\u003eTwitter for Android\u003c\/a\u003e","truncated":false,"in_reply_to_status_id":1286257971392057344,"in_reply_to_status_id_str":"1286257971392057344","in_reply_to_user_id":1282596225099997186,"in_reply_to_user_id_str":"1282596225099997186","in_reply_to_screen_name":"HajerAfrit","user":{"id":2224599883,"id_str":"2224599883","name":"Rabi\u0639a Ben Khedher","screen_name":"Rabiaa999","location":"Tunisia","url":"http:\/\/www.benkhedherrabiaa.com","description":"\u0644\u0627 \u062a\u0633\u0645\u062d \u0644\u0623\u062d\u062f \u0623\u0646 \u064a\u0634\u0639\u0631\u0643 \u0623\u0646\u0643 \u0633\u064a\u0621\u060c \u0623\u0646\u062a \u0623\u0641\u0636\u0644 \u0645\u0646 \u0627\u0644\u0643\u0644\u2764","translator_type":"none","protected":false,"verified":false,"followers_count":1824,"friends_count":4958,"listed_count":2,"favourites_count":9022,"statuses_count":3954,"created_at":"Sun Dec 01 10:02:24 +0000 2013","utc_offset":null,"time_zone":null,"geo_enabled":false,"lang":null,"contributors_enabled":false,"is_translator":false,"profile_background_color":"C6E2EE","profile_background_image_url":"http:\/\/abs.twimg.com\/images\/themes\/theme2\/bg.gif","profile_background_image_url_https":"https:\/\/abs.twimg.com\/images\/themes\/theme2\/bg.gif","profile_background_tile":false,"profile_link_color":"1F98C7","profile_sidebar_border_color":"C6E2EE","profile_sidebar_fill_color":"DAECF4","profile_text_color":"663B12","profile_use_background_image":true,"profile_image_url":"http:\/\/pbs.twimg.com\/profile_images\/1284509600197292034\/NBa8zvzX_normal.jpg","profile_image_url_https":"https:\/\/pbs.twimg.com\/profile_images\/1284509600197292034\/NBa8zvzX_normal.jpg","profile_banner_url":"https:\/\/pbs.twimg.com\/profile_banners\/2224599883\/1595085928","default_profile":false,"default_profile_image":false,"following":null,"follow_request_sent":null,"notifications":null},"geo":null,"coordinates":null,"place":null,"contributors":null,"is_quote_status":false,"quote_count":0,"reply_count":0,"retweet_count":0,"favorite_count":0,"entities":{"hashtags":[],"urls":[],"user_mentions":[{"screen_name":"HajerAfrit","name":"Hajer","id":1282596225099997186,"id_str":"1282596225099997186","indices":[0,11]}],"symbols":[]},"favorited":false,"retweeted":false,"filter_level":"low","lang":"ar","timestamp_ms":"1595502819657"}
