{"created_at":"Thu Jul 23 10:36:37 +0000 2020","id":1286248849221332997,"id_str":"1286248849221332997","text":"RT @MailOnline: Poignant footage shows devoted Palestinian son who climbs hospital to sit outside window of mother's room https:\/\/t.co\/dpYR\u2026","source":"\u003ca href=\"http:\/\/twitter.com\/download\/iphone\" rel=\"nofollow\"\u003eTwitter for iPhone\u003c\/a\u003e","truncated":false,"in_reply_to_status_id":null,"in_reply_to_status_id_str":null,"in_reply_to_user_id":null,"in_reply_to_user_id_str":null,"in_reply_to_screen_name":null,"user":{"id":749377680,"id_str":"749377680","name":"Ak","screen_name":"mr_a_kdr","location":null,"url":null,"description":null,"translator_type":"none","protected":false,"verified":false,"followers_count":107,"friends_count":110,"listed_count":0,"favourites_count":43104,"statuses_count":9412,"created_at":"Fri Aug 10 13:38:52 +0000 2012","utc_offset":null,"time_zone":null,"geo_enabled":false,"lang":null,"contributors_enabled":false,"is_translator":false,"profile_background_color":"C0DEED","profile_background_image_url":"http:\/\/abs.twimg.com\/images\/themes\/theme1\/bg.png","profile_background_image_url_https":"https:\/\/abs.twimg.com\/images\/themes\/theme1\/bg.png","profile_background_tile":false,"profile_link_color":"1DA1F2","profile_sidebar_border_color":"C0DEED","profile_sidebar_fill_color":"DDEEF6","profile_text_color":"333333","profile_use_background_image":true,"profile_image_url":"http:\/\/pbs.twimg.com\/profile_images\/1162169340663422977\/DeU-qBw0_normal.jpg","profile_image_url_https":"https:\/\/pbs.twimg.com\/profile_images\/1162169340663422977\/DeU-qBw0_normal.jpg","default_profile":true,"default_profile_image":false,"following":null,"follow_request_sent":null,"notifications":null},"geo":null,"coordinates":null,"place":null,"contributors":null,"retweeted_status":{"created_at":"Thu Jul 23 09:31:01 +0000 2020","id":1286232339215982593,"id_str":"1286232339215982593","text":"Poignant footage shows devoted Palestinian son who climbs hospital to sit outside window of mother's room https:\/\/t.co\/dpYREdbLE8","source":"\u003ca href=\"http:\/\/www.socialflow.com\" rel=\"nofollow\"\u003eSocialFlow\u003c\/a\u003e","truncated":false,"in_reply_to_status_id":null,"in_reply_to_status_id_str":null,"in_reply_to_user_id":null,"in_reply_to_user_id_str":null,"in_reply_to_screen_name":null,"user":{"id":15438913,"id_str":"15438913","name":"Daily Mail Online","screen_name":"MailOnline","location":null,"url":"http:\/\/www.dailymail.com","description":"For the latest updates on breaking news visit our website http:\/\/www.dailymail.co.uk #seriouslypopular","translator_type":"regular","protected":false,"verified":true,"followers_count":2564614,"friends_count":2289,"listed_count":12673,"favourites_count":659,"statuses_count":329600,"created_at":"Tue Jul 15 10:17:46 +0000 2008","utc_offset":null,"time_zone":null,"geo_enabled":false,"lang":null,"contributors_enabled":false,"is_translator":false,"profile_background_color":"000000","profile_background_image_url":"http:\/\/abs.twimg.com\/images\/themes\/theme1\/bg.png","profile_background_image_url_https":"https:\/\/abs.twimg.com\/images\/themes\/theme1\/bg.png","profile_background_tile":false,"profile_link_color":"004EB3","profile_sidebar_border_color":"FFFFFF","profile_sidebar_fill_color":"E3E3E3","profile_text_color":"333333","profile_use_background_image":true,"profile_image_url":"http:\/\/pbs.twimg.com\/profile_images\/1194268540058193927\/ca-uOgq6_normal.png","profile_image_url_https":"https:\/\/pbs.twimg.com\/profile_images\/1194268540058193927\/ca-uOgq6_normal.png","profile_banner_url":"https:\/\/pbs.twimg.com\/profile_banners\/15438913\/1488911261","default_profile":false,"default_profile_image":false,"following":null,"follow_request_sent":null,"notifications":null},"geo":null,"coordinates":null,"place":null,"contributors":null,"is_quote_status":false,"quote_count":3,"reply_count":6,"retweet_count":19,"favorite_count":88,"entities":{"hashtags":[],"urls":[{"url":"https:\/\/t.co\/dpYREdbLE8","expanded_url":"https:\/\/trib.al\/bQFxKAv","display_url":"trib.al\/bQFxKAv","indices":[106,129]}],"user_mentions":[],"symbols":[]},"favorited":false,"retweeted":false,"possibly_sensitive":false,"filter_level":"low","lang":"en"},"is_quote_status":false,"quote_count":0,"reply_count":0,"retweet_count":0,"favorite_count":0,"entities":{"hashtags":[],"urls":[],"user_mentions":[{"screen_name":"MailOnline","name":"Daily Mail Online","id":15438913,"id_str":"15438913","indices":[3,14]}],"symbols":[]},"favorited":false,"retweeted":false,"filter_level":"low","lang":"en","timestamp_ms":"1595500597659"}
