{"created_at":"Thu Jul 23 10:35:32 +0000 2020","id":1286248576599887872,"id_str":"1286248576599887872","text":"@yolssegovia Es el destino","display_text_range":[13,26],"source":"\u003ca href=\"http:\/\/twitter.com\/download\/iphone\" rel=\"nofollow\"\u003eTwitter for iPhone\u003c\/a\u003e","truncated":false,"in_reply_to_status_id":1286242057565155329,"in_reply_to_status_id_str":"1286242057565155329","in_reply_to_user_id":773859663074951168,"in_reply_to_user_id_str":"773859663074951168","in_reply_to_screen_name":"yolssegovia","user":{"id":3400655079,"id_str":"3400655079","name":"\u00d8LI","screen_name":"omcm_1403","location":"Barcelona, Espa\u00f1a","url":null,"description":"19. Aqu\u00ed me ver\u00e1s hablando de musiquita, series, pelis y cosas irrelevantes que a nadie le importan. \u00bfCuando se acaba esta simulaci\u00f3n? \ud83e\udd21","translator_type":"none","protected":false,"verified":false,"followers_count":303,"friends_count":566,"listed_count":6,"favourites_count":19612,"statuses_count":17169,"created_at":"Sun Aug 02 23:41:56 +0000 2015","utc_offset":null,"time_zone":null,"geo_enabled":true,"lang":null,"contributors_enabled":false,"is_translator":false,"profile_background_color":"C0DEED","profile_background_image_url":"http:\/\/abs.twimg.com\/images\/themes\/theme1\/bg.png","profile_background_image_url_https":"https:\/\/abs.twimg.com\/images\/themes\/theme1\/bg.png","profile_background_tile":false,"profile_link_color":"1DA1F2","profile_sidebar_border_color":"C0DEED","profile_sidebar_fill_color":"DDEEF6","profile_text_color":"333333","profile_use_background_image":true,"profile_image_url":"http:\/\/pbs.twimg.com\/profile_images\/1280267706294571008\/zBdxmHAW_normal.jpg","profile_image_url_https":"https:\/\/pbs.twimg.com\/profile_images\/1280267706294571008\/zBdxmHAW_normal.jpg","profile_banner_url":"https:\/\/pbs.twimg.com\/profile_banners\/3400655079\/1594074583","default_profile":true,"default_profile_image":false,"following":null,"follow_request_sent":null,"notifications":null},"geo":null,"coordinates":null,"place":null,"contributors":null,"is_quote_status":false,"quote_count":0,"reply_count":0,"retweet_count":0,"favorite_count":0,"entities":{"hashtags":[],"urls":[],"user_mentions":[{"screen_name":"yolssegovia","name":"LA YAYA DEL PAREO","id":773859663074951168,"id_str":"773859663074951168","indices":[0,12]}],"symbols":[]},"favorited":false,"retweeted":false,"filter_level":"low","lang":"es","timestamp_ms":"1595500532661"}
