{"created_at":"Thu Jul 23 11:04:35 +0000 2020","id":1286255887263252480,"id_str":"1286255887263252480","text":"RT @feifeiliu77: \u0e17\u0e38\u0e01\u0e04\u0e19\u0e04\u0e30\u0e15\u0e2d\u0e19\u0e19\u0e35\u0e49\u0e04\u0e38\u0e13\u0e17\u0e34\u0e27\u0e32\u0e01\u0e23\u0e44\u0e14\u0e49\u0e23\u0e31\u0e1a\u0e01\u0e32\u0e23\u0e1b\u0e25\u0e48\u0e2d\u0e22\u0e15\u0e31\u0e27\u0e41\u0e25\u0e49\u0e27\u0e04\u0e48\u0e30 \u0e1e\u0e27\u0e01\u0e40\u0e23\u0e32\u0e0a\u0e48\u0e27\u0e22\u0e40\u0e02\u0e32\u0e44\u0e14\u0e49\u0e41\u0e25\u0e49\u0e27\u0e19\u0e30\u0e04\u0e30\ud83d\ude2d #save\u0e17\u0e34\u0e27\u0e32\u0e01\u0e23 https:\/\/t.co\/LqUEsAzAUm","source":"\u003ca href=\"http:\/\/twitter.com\/download\/iphone\" rel=\"nofollow\"\u003eTwitter for iPhone\u003c\/a\u003e","truncated":false,"in_reply_to_status_id":null,"in_reply_to_status_id_str":null,"in_reply_to_user_id":null,"in_reply_to_user_id_str":null,"in_reply_to_screen_name":null,"user":{"id":2578367497,"id_str":"2578367497","name":"f","screen_name":"pwtssd","location":null,"url":null,"description":null,"translator_type":"none","protected":false,"verified":false,"followers_count":246,"friends_count":91,"listed_count":2,"favourites_count":3633,"statuses_count":132486,"created_at":"Fri Jun 20 09:11:19 +0000 2014","utc_offset":null,"time_zone":null,"geo_enabled":true,"lang":null,"contributors_enabled":false,"is_translator":false,"profile_background_color":"ACDED6","profile_background_image_url":"http:\/\/abs.twimg.com\/images\/themes\/theme18\/bg.gif","profile_background_image_url_https":"https:\/\/abs.twimg.com\/images\/themes\/theme18\/bg.gif","profile_background_tile":false,"profile_link_color":"FF691F","profile_sidebar_border_color":"000000","profile_sidebar_fill_color":"000000","profile_text_color":"000000","profile_use_background_image":true,"profile_image_url":"http:\/\/pbs.twimg.com\/profile_images\/869475797442023424\/HMH7HJ6d_normal.jpg","profile_image_url_https":"https:\/\/pbs.twimg.com\/profile_images\/869475797442023424\/HMH7HJ6d_normal.jpg","profile_banner_url":"https:\/\/pbs.twimg.com\/profile_banners\/2578367497\/1496110439","default_profile":false,"default_profile_image":false,"following":null,"follow_request_sent":null,"notifications":null},"geo":null,"coordinates":null,"place":null,"contributors":null,"retweeted_status":{"created_at":"Wed Jul 22 13:14:58 +0000 2020","id":1285926312406732800,"id_str":"1285926312406732800","text":"\u0e17\u0e38\u0e01\u0e04\u0e19\u0e04\u0e30\u0e15\u0e2d\u0e19\u0e19\u0e35\u0e49\u0e04\u0e38\u0e13\u0e17\u0e34\u0e27\u0e32\u0e01\u0e23\u0e44\u0e14\u0e49\u0e23\u0e31\u0e1a\u0e01\u0e32\u0e23\u0e1b\u0e25\u0e48\u0e2d\u0e22\u0e15\u0e31\u0e27\u0e41\u0e25\u0e49\u0e27\u0e04\u0e48\u0e30 \u0e1e\u0e27\u0e01\u0e40\u0e23\u0e32\u0e0a\u0e48\u0e27\u0e22\u0e40\u0e02\u0e32\u0e44\u0e14\u0e49\u0e41\u0e25\u0e49\u0e27\u0e19\u0e30\u0e04\u0e30\ud83d\ude2d #save\u0e17\u0e34\u0e27\u0e32\u0e01\u0e23 https:\/\/t.co\/LqUEsAzAUm","display_text_range":[0,84],"source":"\u003ca href=\"http:\/\/twitter.com\/download\/iphone\" rel=\"nofollow\"\u003eTwitter for iPhone\u003c\/a\u003e","truncated":false,"in_reply_to_status_id":null,"in_reply_to_status_id_str":null,"in_reply_to_user_id":null,"in_reply_to_user_id_str":null,"in_reply_to_screen_name":null,"user":{"id":730296766491320321,"id_str":"730296766491320321","name":"\u0e2b\u0e25\u0e34\u0e27\u0e19\u0e39\u0e19\u0e48\u0e32 lll","screen_name":"feifeiliu77","location":"jaeyong dotae ","url":null,"description":"\u0e2d\u0e32\u0e22\u0e38\u0e2a\u0e31\u0e49\u0e19 \u0e2a\u0e31\u0e19\u0e2b\u0e25\u0e31\u0e07\u0e22\u0e32\u0e27","translator_type":"none","protected":false,"verified":false,"followers_count":2728,"friends_count":278,"listed_count":2,"favourites_count":2957,"statuses_count":72549,"created_at":"Wed May 11 07:21:32 +0000 2016","utc_offset":null,"time_zone":null,"geo_enabled":true,"lang":null,"contributors_enabled":false,"is_translator":false,"profile_background_color":"000000","profile_background_image_url":"http:\/\/abs.twimg.com\/images\/themes\/theme1\/bg.png","profile_background_image_url_https":"https:\/\/abs.twimg.com\/images\/themes\/theme1\/bg.png","profile_background_tile":false,"profile_link_color":"E81C4F","profile_sidebar_border_color":"000000","profile_sidebar_fill_color":"000000","profile_text_color":"000000","profile_use_background_image":false,"profile_image_url":"http:\/\/pbs.twimg.com\/profile_images\/1284036015712346119\/EL-WJOnx_normal.jpg","profile_image_url_https":"https:\/\/pbs.twimg.com\/profile_images\/1284036015712346119\/EL-WJOnx_normal.jpg","profile_banner_url":"https:\/\/pbs.twimg.com\/profile_banners\/730296766491320321\/1595155258","default_profile":false,"default_profile_image":false,"following":null,"follow_request_sent":null,"notifications":null},"geo":null,"coordinates":null,"place":null,"contributors":null,"is_quote_status":false,"quote_count":22,"reply_count":4,"retweet_count":6667,"favorite_count":972,"entities":{"hashtags":[{"text":"save\u0e17\u0e34\u0e27\u0e32\u0e01\u0e23","indices":[73,84]}],"urls":[],"user_mentions":[],"symbols":[],"media":[{"id":1285926305528049665,"id_str":"1285926305528049665","indices":[85,108],"media_url":"http:\/\/pbs.twimg.com\/media\/EdiHKWhUcAEEYQu.jpg","media_url_https":"https:\/\/pbs.twimg.com\/media\/EdiHKWhUcAEEYQu.jpg","url":"https:\/\/t.co\/LqUEsAzAUm","display_url":"pic.twitter.com\/LqUEsAzAUm","expanded_url":"https:\/\/twitter.com\/feifeiliu77\/status\/1285926312406732800\/photo\/1","type":"photo","sizes":{"large":{"w":720,"h":960,"resize":"fit"},"thumb":{"w":150,"h":150,"resize":"crop"},"medium":{"w":720,"h":960,"resize":"fit"},"small":{"w":510,"h":680,"resize":"fit"}}}]},"extended_entities":{"media":[{"id":1285926305528049665,"id_str":"1285926305528049665","indices":[85,108],"media_url":"http:\/\/pbs.twimg.com\/media\/EdiHKWhUcAEEYQu.jpg","media_url_https":"https:\/\/pbs.twimg.com\/media\/EdiHKWhUcAEEYQu.jpg","url":"https:\/\/t.co\/LqUEsAzAUm","display_url":"pic.twitter.com\/LqUEsAzAUm","expanded_url":"https:\/\/twitter.com\/feifeiliu77\/status\/1285926312406732800\/photo\/1","type":"photo","sizes":{"large":{"w":720,"h":960,"resize":"fit"},"thumb":{"w":150,"h":150,"resize":"crop"},"medium":{"w":720,"h":960,"resize":"fit"},"small":{"w":510,"h":680,"resize":"fit"}}},{"id":1285926305536458752,"id_str":"1285926305536458752","indices":[85,108],"media_url":"http:\/\/pbs.twimg.com\/media\/EdiHKWjUwAAKcWk.jpg","media_url_https":"https:\/\/pbs.twimg.com\/media\/EdiHKWjUwAAKcWk.jpg","url":"https:\/\/t.co\/LqUEsAzAUm","display_url":"pic.twitter.com\/LqUEsAzAUm","expanded_url":"https:\/\/twitter.com\/feifeiliu77\/status\/1285926312406732800\/photo\/1","type":"photo","sizes":{"medium":{"w":960,"h":720,"resize":"fit"},"thumb":{"w":150,"h":150,"resize":"crop"},"large":{"w":960,"h":720,"resize":"fit"},"small":{"w":680,"h":510,"resize":"fit"}}},{"id":1285926305557475328,"id_str":"1285926305557475328","indices":[85,108],"media_url":"http:\/\/pbs.twimg.com\/media\/EdiHKWoVcAAnFVS.jpg","media_url_https":"https:\/\/pbs.twimg.com\/media\/EdiHKWoVcAAnFVS.jpg","url":"https:\/\/t.co\/LqUEsAzAUm","display_url":"pic.twitter.com\/LqUEsAzAUm","expanded_url":"https:\/\/twitter.com\/feifeiliu77\/status\/1285926312406732800\/photo\/1","type":"photo","sizes":{"large":{"w":720,"h":960,"resize":"fit"},"thumb":{"w":150,"h":150,"resize":"crop"},"medium":{"w":720,"h":960,"resize":"fit"},"small":{"w":510,"h":680,"resize":"fit"}}}]},"favorited":false,"retweeted":false,"possibly_sensitive":false,"filter_level":"low","lang":"th"},"is_quote_status":false,"quote_count":0,"reply_count":0,"retweet_count":0,"favorite_count":0,"entities":{"hashtags":[{"text":"save\u0e17\u0e34\u0e27\u0e32\u0e01\u0e23","indices":[90,101]}],"urls":[],"user_mentions":[{"screen_name":"feifeiliu77","name":"\u0e2b\u0e25\u0e34\u0e27\u0e19\u0e39\u0e19\u0e48\u0e32 lll","id":730296766491320321,"id_str":"730296766491320321","indices":[3,15]}],"symbols":[],"media":[{"id":1285926305528049665,"id_str":"1285926305528049665","indices":[102,125],"media_url":"http:\/\/pbs.twimg.com\/media\/EdiHKWhUcAEEYQu.jpg","media_url_https":"https:\/\/pbs.twimg.com\/media\/EdiHKWhUcAEEYQu.jpg","url":"https:\/\/t.co\/LqUEsAzAUm","display_url":"pic.twitter.com\/LqUEsAzAUm","expanded_url":"https:\/\/twitter.com\/feifeiliu77\/status\/1285926312406732800\/photo\/1","type":"photo","sizes":{"large":{"w":720,"h":960,"resize":"fit"},"thumb":{"w":150,"h":150,"resize":"crop"},"medium":{"w":720,"h":960,"resize":"fit"},"small":{"w":510,"h":680,"resize":"fit"}},"source_status_id":1285926312406732800,"source_status_id_str":"1285926312406732800","source_user_id":730296766491320321,"source_user_id_str":"730296766491320321"}]},"extended_entities":{"media":[{"id":1285926305528049665,"id_str":"1285926305528049665","indices":[102,125],"media_url":"http:\/\/pbs.twimg.com\/media\/EdiHKWhUcAEEYQu.jpg","media_url_https":"https:\/\/pbs.twimg.com\/media\/EdiHKWhUcAEEYQu.jpg","url":"https:\/\/t.co\/LqUEsAzAUm","display_url":"pic.twitter.com\/LqUEsAzAUm","expanded_url":"https:\/\/twitter.com\/feifeiliu77\/status\/1285926312406732800\/photo\/1","type":"photo","sizes":{"large":{"w":720,"h":960,"resize":"fit"},"thumb":{"w":150,"h":150,"resize":"crop"},"medium":{"w":720,"h":960,"resize":"fit"},"small":{"w":510,"h":680,"resize":"fit"}},"source_status_id":1285926312406732800,"source_status_id_str":"1285926312406732800","source_user_id":730296766491320321,"source_user_id_str":"730296766491320321"},{"id":1285926305536458752,"id_str":"1285926305536458752","indices":[102,125],"media_url":"http:\/\/pbs.twimg.com\/media\/EdiHKWjUwAAKcWk.jpg","media_url_https":"https:\/\/pbs.twimg.com\/media\/EdiHKWjUwAAKcWk.jpg","url":"https:\/\/t.co\/LqUEsAzAUm","display_url":"pic.twitter.com\/LqUEsAzAUm","expanded_url":"https:\/\/twitter.com\/feifeiliu77\/status\/1285926312406732800\/photo\/1","type":"photo","sizes":{"medium":{"w":960,"h":720,"resize":"fit"},"thumb":{"w":150,"h":150,"resize":"crop"},"large":{"w":960,"h":720,"resize":"fit"},"small":{"w":680,"h":510,"resize":"fit"}},"source_status_id":1285926312406732800,"source_status_id_str":"1285926312406732800","source_user_id":730296766491320321,"source_user_id_str":"730296766491320321"},{"id":1285926305557475328,"id_str":"1285926305557475328","indices":[102,125],"media_url":"http:\/\/pbs.twimg.com\/media\/EdiHKWoVcAAnFVS.jpg","media_url_https":"https:\/\/pbs.twimg.com\/media\/EdiHKWoVcAAnFVS.jpg","url":"https:\/\/t.co\/LqUEsAzAUm","display_url":"pic.twitter.com\/LqUEsAzAUm","expanded_url":"https:\/\/twitter.com\/feifeiliu77\/status\/1285926312406732800\/photo\/1","type":"photo","sizes":{"large":{"w":720,"h":960,"resize":"fit"},"thumb":{"w":150,"h":150,"resize":"crop"},"medium":{"w":720,"h":960,"resize":"fit"},"small":{"w":510,"h":680,"resize":"fit"}},"source_status_id":1285926312406732800,"source_status_id_str":"1285926312406732800","source_user_id":730296766491320321,"source_user_id_str":"730296766491320321"}]},"favorited":false,"retweeted":false,"possibly_sensitive":false,"filter_level":"low","lang":"th","timestamp_ms":"1595502275659"}
